sec_edgar_py/__init__.py
sec_edgar_py/sec_edgar.py
sec_edgar_py-0.0.4.dist-info/LICENSE
sec_edgar_py-0.0.4.dist-info/METADATA
sec_edgar_py-0.0.4.dist-info/WHEEL
sec_edgar_py-0.0.4.dist-info/top_level.txt
sec_edgar_py-0.0.4.dist-info/RECORD
