Metadata-Version: 2.1
Name: sec-edgar-py
Version: 0.0.4
Summary: A basic (unofficial) Python API wrapper for the SECs EDGAR system
Home-page: https://github.com/robin-weaver/sec-edgar.py
Author: Robin Weaver
Author-email: robinweaver2001@gmail.com
Project-URL: Bug Tracker, https://github.com/robin-weaver/sec-edgar.py/issues
Classifier: Programming Language :: Python :: 3
Classifier: License :: OSI Approved :: GNU General Public License v3 (GPLv3)
Classifier: Operating System :: OS Independent
Requires-Python: >=3.6
License-File: LICENSE
